nichejepa/__init__.py
nichejepa/models/__init__.py
nichejepa/tokenizers/__init__.py
nichejepa/tokenizers/st_rank_tokenizer.py
nichejepa/utils/__init__.py
nichejepa/utils/genes.py
nichejepa-0.0.0.dist-info/METADATA
nichejepa-0.0.0.dist-info/WHEEL
nichejepa-0.0.0.dist-info/licenses/LICENSE
nichejepa-0.0.0.dist-info/RECORD
