Metadata-Version: 2.3
Name: nichejepa
Version: 0.0.0
Summary: Spatial omics foundation model
Project-URL: Documentation, https://niche-jepa.readthedocs.io/
Project-URL: Source, https://github.com/Lotfollahi-lab/niche-jepa
Project-URL: Home-page, https://github.com/Lotfollahi-lab/niche-jepa
Author: Sebastian Birk
Maintainer-email: Sebastian Birk <sebastian.birk@helmholtz-munich.de>
License: BSD 3-Clause License
License-File: LICENSE
Requires-Python: >=3.10
Requires-Dist: anndata
Requires-Dist: datasets
Requires-Dist: session-info
Requires-Dist: squidpy
Provides-Extra: dev
Requires-Dist: pre-commit; extra == 'dev'
Requires-Dist: twine>=4.0.2; extra == 'dev'
Provides-Extra: doc
Requires-Dist: docutils!=0.18.*,!=0.19.*,>=0.8; extra == 'doc'
Requires-Dist: ipykernel; extra == 'doc'
Requires-Dist: ipython; extra == 'doc'
Requires-Dist: myst-nb; extra == 'doc'
Requires-Dist: pandas; extra == 'doc'
Requires-Dist: sphinx-autodoc-typehints; extra == 'doc'
Requires-Dist: sphinx-book-theme>=1.0.0; extra == 'doc'
Requires-Dist: sphinx-copybutton; extra == 'doc'
Requires-Dist: sphinx>=4; extra == 'doc'
Requires-Dist: sphinxcontrib-bibtex>=1.0.0; extra == 'doc'
Requires-Dist: sphinxext-opengraph; extra == 'doc'
Provides-Extra: test
Requires-Dist: coverage; extra == 'test'
Requires-Dist: pytest; extra == 'test'
